mongodb_connect/__init__.py
mongodb_connect/mongo_crud.py
mongo_bridge-0.0.6.dist-info/LICENSE
mongo_bridge-0.0.6.dist-info/METADATA
mongo_bridge-0.0.6.dist-info/WHEEL
mongo_bridge-0.0.6.dist-info/top_level.txt
mongo_bridge-0.0.6.dist-info/RECORD
