Metadata-Version: 2.1
Name: mongo_bridge
Version: 0.0.6
Summary: A python package for connecting with database.
Home-page: https://github.com/Vansh353/MongoDB
Author: Vansh353
Author-email: vansh.malhotra@seaflux.tech
License: MIT
Project-URL: Bug Tracker, https://github.com/Vansh353/MongoDB/issues
Classifier: Programming Language :: Python :: 3.11
Classifier: Operating System :: OS Independent
License-File: LICENSE
Requires-Dist: pymongo
Requires-Dist: dnspython
Requires-Dist: pandas
Requires-Dist: numpy
Requires-Dist: ensure
Requires-Dist: pytest
Requires-Dist: tox
Provides-Extra: testing
Requires-Dist: pytest >=7.1.3 ; extra == 'testing'
Requires-Dist: mypy >=0.971 ; extra == 'testing'
Requires-Dist: flake8 >=5.0.4 ; extra == 'testing'
Requires-Dist: black >=22.8.0 ; extra == 'testing'
